[
  {
    "CustomerTransactionID": 34,
    "CustomerID": 1,
    "TransactionDate": "2013-01-01T00:00:00",
    "AmountExcludingTax": 104.00,
    "TaxAmount": 15.60,
    "TransactionAmount": 119.60,
    "OutstandingBalance": 0.00,
    "FinalizationDate": "2013-01-02T00:00:00",
    "InvoiceID": 10,
    "StockItemID": 38,
    "Quantity": 5,
    "UnitPrice": 13.00
  },
  {
    "CustomerTransactionID": 34,
    "CustomerID": 1,
    "TransactionDate": "2013-01-01T00:00:00",
    "AmountExcludingTax": 104.00,
    "TaxAmount": 15.60,
    "TransactionAmount": 119.60,
    "OutstandingBalance": 0.00,
    "FinalizationDate": "2013-01-02T00:00:00",
    "InvoiceID": 10,
    "StockItemID": 34,
    "Quantity": 3,
    "UnitPrice": 13.00
  },
  {
    "CustomerTransactionID": 36,
    "CustomerID": 401,
    "TransactionDate": "2013-01-01T00:00:00",
    "AmountExcludingTax": 13.00,
    "TaxAmount": 1.95,
    "TransactionAmount": 14.95,
    "OutstandingBalance": 0.00,
    "FinalizationDate": "2013-01-02T00:00:00",
    "InvoiceID": 11,
    "StockItemID": 45,
    "Quantity": 1,
    "UnitPrice": 13.00
  },
  {
    "CustomerTransactionID": 39,
    "CustomerID": 401,
    "TransactionDate": "2013-01-01T00:00:00",
    "AmountExcludingTax": 229.00,
    "TaxAmount": 34.35,
    "TransactionAmount": 263.35,
    "OutstandingBalance": 0.00,
    "FinalizationDate": "2013-01-02T00:00:00",
    "InvoiceID": 12,
    "StockItemID": 62,
    "Quantity": 5,
    "UnitPrice": 25.00
  },
  {
    "CustomerTransactionID": 39,
    "CustomerID": 401,
    "TransactionDate": "2013-01-01T00:00:00",
    "AmountExcludingTax": 229.00,
    "TaxAmount": 34.35,
    "TransactionAmount": 263.35,
    "OutstandingBalance": 0.00,
    "FinalizationDate": "2013-01-02T00:00:00",
    "InvoiceID": 12,
    "StockItemID": 44,
    "Quantity": 8,
    "UnitPrice": 13.00
  },
  {
    "CustomerTransactionID": 42,
    "CustomerID": 401,
    "TransactionDate": "2013-01-01T00:00:00",
    "AmountExcludingTax": 2430.00,
    "TaxAmount": 364.50,
    "TransactionAmount": 2794.50,
    "OutstandingBalance": 0.00,
    "FinalizationDate": "2013-01-02T00:00:00",
    "InvoiceID": 13,
    "StockItemID": 156,
    "Quantity": 10,
    "UnitPrice": 15.00
  },
  {
    "CustomerTransactionID": 42,
    "CustomerID": 401,
    "TransactionDate": "2013-01-01T00:00:00",
    "AmountExcludingTax": 2430.00,
    "TaxAmount": 364.50,
    "TransactionAmount": 2794.50,
    "OutstandingBalance": 0.00,
    "FinalizationDate": "2013-01-02T00:00:00",
    "InvoiceID": 13,
    "StockItemID": 73,
    "Quantity": 8,
    "UnitPrice": 285.00
  },
  {
    "CustomerTransactionID": 46,
    "CustomerID": 870,
    "TransactionDate": "2013-01-01T00:00:00",
    "AmountExcludingTax": 650.00,
    "TaxAmount": 97.50,
    "TransactionAmount": 747.50,
    "OutstandingBalance": 0.00,
    "FinalizationDate": "2013-01-02T00:00:00",
    "InvoiceID": 14,
    "StockItemID": 111,
    "Quantity": 4,
    "UnitPrice": 30.00
  },
  {
    "CustomerTransactionID": 46,
    "CustomerID": 870,
    "TransactionDate": "2013-01-01T00:00:00",
    "AmountExcludingTax": 650.00,
    "TaxAmount": 97.50,
    "TransactionAmount": 747.50,
    "OutstandingBalance": 0.00,
    "FinalizationDate": "2013-01-02T00:00:00",
    "InvoiceID": 14,
    "StockItemID": 163,
    "Quantity": 10,
    "UnitPrice": 37.00
  },
  {
    "CustomerTransactionID": 46,
    "CustomerID": 870,
    "TransactionDate": "2013-01-01T00:00:00",
    "AmountExcludingTax": 650.00,
    "TaxAmount": 97.50,
    "TransactionAmount": 747.50,
    "OutstandingBalance": 0.00,
    "FinalizationDate": "2013-01-02T00:00:00",
    "InvoiceID": 14,
    "StockItemID": 132,
    "Quantity": 5,
    "UnitPrice": 32.00
  },
  {
    "CustomerTransactionID": 49,
    "CustomerID": 991,
    "TransactionDate": "2013-01-01T00:00:00",
    "AmountExcludingTax": 174.00,
    "TaxAmount": 26.10,
    "TransactionAmount": 200.10,
    "OutstandingBalance": 0.00,
    "FinalizationDate": "2013-01-02T00:00:00",
    "InvoiceID": 15,
    "StockItemID": 108,
    "Quantity": 6,
    "UnitPrice": 25.00
  },
  {
    "CustomerTransactionID": 49,
    "CustomerID": 991,
    "TransactionDate": "2013-01-01T00:00:00",
    "AmountExcludingTax": 174.00,
    "TaxAmount": 26.10,
    "TransactionAmount": 200.10,
    "OutstandingBalance": 0.00,
    "FinalizationDate": "2013-01-02T00:00:00",
    "InvoiceID": 15,
    "StockItemID": 210,
    "Quantity": 10,
    "UnitPrice": 2.40
  },
  {
    "CustomerTransactionID": 51,
    "CustomerID": 401,
    "TransactionDate": "2013-01-01T00:00:00",
    "AmountExcludingTax": 68.00,
    "TaxAmount": 10.20,
    "TransactionAmount": 78.20,
    "OutstandingBalance": 0.00,
    "FinalizationDate": "2013-01-02T00:00:00",
    "InvoiceID": 16,
    "StockItemID": 115,
    "Quantity": 2,
    "UnitPrice": 34.00
  },
  {
    "CustomerTransactionID": 54,
    "CustomerID": 910,
    "TransactionDate": "2013-01-01T00:00:00",
    "AmountExcludingTax": 424.00,
    "TaxAmount": 63.60,
    "TransactionAmount": 487.60,
    "OutstandingBalance": 0.00,
    "FinalizationDate": "2013-01-02T00:00:00",
    "InvoiceID": 17,
    "StockItemID": 133,
    "Quantity": 10,
    "UnitPrice": 32.00
  },
  {
    "CustomerTransactionID": 54,
    "CustomerID": 910,
    "TransactionDate": "2013-01-01T00:00:00",
    "AmountExcludingTax": 424.00,
    "TaxAmount": 63.60,
    "TransactionAmount": 487.60,
    "OutstandingBalance": 0.00,
    "FinalizationDate": "2013-01-02T00:00:00",
    "InvoiceID": 17,
    "StockItemID": 47,
    "Quantity": 8,
    "UnitPrice": 13.00
  },
  {
    "CustomerTransactionID": 56,
    "CustomerID": 949,
    "TransactionDate": "2013-01-01T00:00:00",
    "AmountExcludingTax": 91.00,
    "TaxAmount": 13.65,
    "TransactionAmount": 104.65,
    "OutstandingBalance": 0.00,
    "FinalizationDate": "2013-01-02T00:00:00",
    "InvoiceID": 18,
    "StockItemID": 22,
    "Quantity": 7,
    "UnitPrice": 13.00
  },
  {
    "CustomerTransactionID": 60,
    "CustomerID": 973,
    "TransactionDate": "2013-01-01T00:00:00",
    "AmountExcludingTax": 3185.00,
    "TaxAmount": 477.75,
    "TransactionAmount": 3662.75,
    "OutstandingBalance": 0.00,
    "FinalizationDate": "2013-01-02T00:00:00",
    "InvoiceID": 19,
    "StockItemID": 15,
    "Quantity": 8,
    "UnitPrice": 240.00
  },
  {
    "CustomerTransactionID": 60,
    "CustomerID": 973,
    "TransactionDate": "2013-01-01T00:00:00",
    "AmountExcludingTax": 3185.00,
    "TaxAmount": 477.75,
    "TransactionAmount": 3662.75,
    "OutstandingBalance": 0.00,
    "FinalizationDate": "2013-01-02T00:00:00",
    "InvoiceID": 19,
    "StockItemID": 75,
    "Quantity": 1,
    "UnitPrice": 345.00
  },
  {
    "CustomerTransactionID": 60,
    "CustomerID": 973,
    "TransactionDate": "2013-01-01T00:00:00",
    "AmountExcludingTax": 3185.00,
    "TaxAmount": 477.75,
    "TransactionAmount": 3662.75,
    "OutstandingBalance": 0.00,
    "FinalizationDate": "2013-01-02T00:00:00",
    "InvoiceID": 19,
    "StockItemID": 68,
    "Quantity": 4,
    "UnitPrice": 230.00
  },
  {
    "CustomerTransactionID": 62,
    "CustomerID": 884,
    "TransactionDate": "2013-01-01T00:00:00",
    "AmountExcludingTax": 240.00,
    "TaxAmount": 36.00,
    "TransactionAmount": 276.00,
    "OutstandingBalance": 0.00,
    "FinalizationDate": "2013-01-02T00:00:00",
    "InvoiceID": 20,
    "StockItemID": 111,
    "Quantity": 8,
    "UnitPrice": 30.00
  }
]